<?xml version="1.0" ?><ItemLookupResponse xmlns="http://webservices.amazon.com/AWSECommerceService/2011-08-01"><OperationRequest><HTTPHeaders><Header Name="UserAgent" Value="python-requests/2.10.0"></Header></HTTPHeaders><RequestId>789253e9-75f2-4460-84ea-f5b1c4ffe263</RequestId><Arguments><Argument Name="AWSAccessKeyId" Value="AKIAJIKVGLZ2P37DL2EQ"></Argument><Argument Name="AssociateTag" Value="wengyusu-22"></Argument><Argument Name="IdType" Value="ASIN"></Argument><Argument Name="ItemId" Value="B015ZAEGM2"></Argument><Argument Name="Operation" Value="ItemLookup"></Argument><Argument Name="ResponseGroup" Value="ItemAttributes,SalesRank"></Argument><Argument Name="Service" Value="AWSECommerceService"></Argument><Argument Name="Timestamp" Value="2016-05-22T12:01:38Z"></Argument><Argument Name="Signature" Value="w0GxJ4ZdJPnXj7RSJrMgZjU3KggwP/CMk0NKHjWpuhE="></Argument></Arguments><RequestProcessingTime>0.0104273530000000</RequestProcessingTime></OperationRequest><Items><Request><IsValid>True</IsValid><ItemLookupRequest><IdType>ASIN</IdType><ItemId>B015ZAEGM2</ItemId><ResponseGroup>ItemAttributes</ResponseGroup><ResponseGroup>SalesRank</ResponseGroup><VariationPage>All</VariationPage></ItemLookupRequest></Request><Item><ASIN>B015ZAEGM2</ASIN><DetailPageURL>http://www.amazon.co.jp/%E3%83%AF%E3%83%B3%E3%83%91%E3%83%B3%E3%83%9E%E3%83%B3-6-%E7%89%B9%E8%A3%85%E9%99%90%E5%AE%9A%E7%89%88-Blu-ray-%E5%8F%A4%E5%B7%9D%E6%85%8E/dp/B015ZAEGM2%3FSubscriptionId%3DAKIAJIKVGLZ2P37DL2EQ%26tag%3Dwengyusu-22%26linkCode%3Dxm2%26camp%3D2025%26creative%3D165953%26creativeASIN%3DB015ZAEGM2</DetailPageURL><ItemLinks><ItemLink><Description>Add To Wishlist</Description><URL>http://www.amazon.co.jp/gp/registry/wishlist/add-item.html%3Fasin.0%3DB015ZAEGM2%26SubscriptionId%3DAKIAJIKVGLZ2P37DL2EQ%26tag%3Dwengyusu-22%26linkCode%3Dxm2%26camp%3D2025%26creative%3D5143%26creativeASIN%3DB015ZAEGM2</URL></ItemLink><ItemLink><Description>Tell A Friend</Description><URL>http://www.amazon.co.jp/gp/pdp/taf/B015ZAEGM2%3FSubscriptionId%3DAKIAJIKVGLZ2P37DL2EQ%26tag%3Dwengyusu-22%26linkCode%3Dxm2%26camp%3D2025%26creative%3D5143%26creativeASIN%3DB015ZAEGM2</URL></ItemLink><ItemLink><Description>All Customer Reviews</Description><URL>http://www.amazon.co.jp/review/product/B015ZAEGM2%3FSubscriptionId%3DAKIAJIKVGLZ2P37DL2EQ%26tag%3Dwengyusu-22%26linkCode%3Dxm2%26camp%3D2025%26creative%3D5143%26creativeASIN%3DB015ZAEGM2</URL></ItemLink><ItemLink><Description>All Offers</Description><URL>http://www.amazon.co.jp/gp/offer-listing/B015ZAEGM2%3FSubscriptionId%3DAKIAJIKVGLZ2P37DL2EQ%26tag%3Dwengyusu-22%26linkCode%3Dxm2%26camp%3D2025%26creative%3D5143%26creativeASIN%3DB015ZAEGM2</URL></ItemLink></ItemLinks><SalesRank>240</SalesRank><ItemAttributes><Actor>古川慎</Actor><Actor>石川界人</Actor><Actor>中尾隆聖</Actor><AspectRatio>1.78:1</AspectRatio><Binding>Blu-ray</Binding><Director>夏目真悟</Director><EAN>4934569360434</EAN><EANList><EANListElement>4934569360434</EANListElement></EANList><Format>Color</Format><Format>Limited Edition</Format><Format>Widescreen</Format><IsAdultProduct>0</IsAdultProduct><ItemDimensions><Height Units="hundredths-inches">709</Height><Length Units="hundredths-inches">984</Length><Weight Units="hundredths-pounds">110</Weight><Width Units="hundredths-inches">87</Width></ItemDimensions><Label>バンダイビジュアル</Label><ListPrice><Amount>7560</Amount><CurrencyCode>JPY</CurrencyCode><FormattedPrice>￥ 7,560</FormattedPrice></ListPrice><Manufacturer>バンダイビジュアル</Manufacturer><NumberOfDiscs>2</NumberOfDiscs><NumberOfItems>2</NumberOfItems><PackageDimensions><Height Units="hundredths-inches">87</Height><Length Units="hundredths-inches">984</Length><Weight Units="hundredths-pounds">110</Weight><Width Units="hundredths-inches">709</Width></PackageDimensions><ProductGroup>DVD</ProductGroup><ProductTypeName>ABIS_DVD</ProductTypeName><Publisher>バンダイビジュアル</Publisher><ReleaseDate>2016-05-27</ReleaseDate><RunningTime Units="分">95</RunningTime><SeikodoProductCode>BCXA-1043</SeikodoProductCode><Studio>バンダイビジュアル</Studio><Title>ワンパンマン 6 (特装限定版) [Blu-ray]</Title></ItemAttributes></Item></Items></ItemLookupResponse>